odoo10_addon_partner_employee_quantity-10.0.1.0.0-py2.7-nspkg.pth
odoo/addons/partner_employee_quantity/README.rst
odoo/addons/partner_employee_quantity/__init__.py
odoo/addons/partner_employee_quantity/__manifest__.py
odoo/addons/partner_employee_quantity/i18n/de.po
odoo/addons/partner_employee_quantity/i18n/es.po
odoo/addons/partner_employee_quantity/i18n/eu.po
odoo/addons/partner_employee_quantity/i18n/fi.po
odoo/addons/partner_employee_quantity/i18n/it.po
odoo/addons/partner_employee_quantity/i18n/sl.po
odoo/addons/partner_employee_quantity/models/__init__.py
odoo/addons/partner_employee_quantity/models/res_partner.py
odoo/addons/partner_employee_quantity/security/ir.model.access.csv
odoo/addons/partner_employee_quantity/static/description/icon.png
odoo/addons/partner_employee_quantity/views/res_partner_employee_quantity_range_view.xml
odoo/addons/partner_employee_quantity/views/res_partner_view.xml
odoo10_addon_partner_employee_quantity-10.0.1.0.0.dist-info/DESCRIPTION.rst
odoo10_addon_partner_employee_quantity-10.0.1.0.0.dist-info/METADATA
odoo10_addon_partner_employee_quantity-10.0.1.0.0.dist-info/RECORD
odoo10_addon_partner_employee_quantity-10.0.1.0.0.dist-info/WHEEL
odoo10_addon_partner_employee_quantity-10.0.1.0.0.dist-info/metadata.json
odoo10_addon_partner_employee_quantity-10.0.1.0.0.dist-info/namespace_packages.txt
odoo10_addon_partner_employee_quantity-10.0.1.0.0.dist-info/top_level.txt
